pylife/rainflow_ext.cpython-313-x86_64-linux-gnu.so
pylife/__init__.py
pylife/utils/histogram.py
pylife/utils/README.md
pylife/utils/functions.py
pylife/utils/probability_data.py
pylife/utils/__init__.py
pylife/vmap/vmap_section.py
pylife/vmap/vmap_unit_system.py
pylife/vmap/vmap_export.py
pylife/vmap/vmap_import.py
pylife/vmap/vmap_integration_type.py
pylife/vmap/exceptions.py
pylife/vmap/vmap_dataset.py
pylife/vmap/vmap_metadata.py
pylife/vmap/vmap_attribute.py
pylife/vmap/__init__.py
pylife/vmap/vmap_structures.py
pylife/vmap/vmap_element_type.py
pylife/vmap/vmap_coordinate_system.py
pylife/stress/frequencysignal.py
pylife/stress/README.md
pylife/stress/timesignal.py
pylife/stress/stresssignal.py
pylife/stress/equistress.py
pylife/stress/__init__.py
pylife/stress/rainflow/general.py
pylife/stress/rainflow/recorders.py
pylife/stress/rainflow/.gitignore
pylife/stress/rainflow/fkm.py
pylife/stress/rainflow/fourpoint.py
pylife/stress/rainflow/extension.pyx
pylife/stress/rainflow/threepoint.py
pylife/stress/rainflow/compat.py
pylife/stress/rainflow/__init__.py
pylife/stress/collective/load_collective.py
pylife/stress/collective/abstract_load_collective.py
pylife/stress/collective/load_histogram.py
pylife/stress/collective/__init__.py
pylife/materiallaws/hookeslaw.py
pylife/materiallaws/woehlercurve.py
pylife/materiallaws/true_stress_strain.py
pylife/materiallaws/__init__.py
pylife/materiallaws/rambgood.py
pylife/mesh/hotspot.py
pylife/mesh/gradient.py
pylife/mesh/meshmapping.py
pylife/mesh/meshsignal.py
pylife/mesh/__init__.py
pylife/materialdata/.gitignore
pylife/materialdata/__init__.py
pylife/materialdata/data/Test_dat.xlsx
pylife/materialdata/woehler/bayesian.py
pylife/materialdata/woehler/maxlike.py
pylife/materialdata/woehler/likelihood.py
pylife/materialdata/woehler/pymc_dummy.py
pylife/materialdata/woehler/probit.py
pylife/materialdata/woehler/pearl_chain.py
pylife/materialdata/woehler/elementary.py
pylife-2.1.4.dist-info/WHEEL
pylife-2.1.4.dist-info/top_level.txt
pylife-2.1.4.dist-info/METADATA
pylife-2.1.4.dist-info/RECORD
pylife-2.1.4.dist-info/licenses/NOTICE
pylife-2.1.4.dist-info/licenses/LICENSE
