Metadata-Version: 2.4
Name: pylife
Version: 2.1.4
Summary: General Fatigue library
Home-page: https://github.com/boschresearch/pylife/
Author: pyLife developer team @ Bosch Research
Author-email: "pyLife developer team @ Bosch Research" <johannes.mueller4@de.bosch.com>
License: Apache-2
Project-URL: Homepage, https://github.com/boschresearch/pylife/
Project-URL: Documentation, https://pylife.readthedocs.io
Project-URL: Source, https://github.com/boschresearch/pylife/
Project-URL: Changelog, https://pylife.readthedocs.io/en/stable/CHANGELOG.html
Project-URL: Tracker, https://github.com/boschresearch/pylife/issues
Project-URL: Download, https://pypi.org/project/pylife/#files
Platform: any
Classifier: Development Status :: 4 - Beta
Classifier: Programming Language :: Python :: 3
Classifier: License :: OSI Approved :: Apache Software License
Classifier: Operating System :: OS Independent
Requires-Python: >=3.9
License-File: LICENSE
License-File: NOTICE
Requires-Dist: numpy>=1.23.5
Requires-Dist: scipy
Requires-Dist: pandas>=2.2
Requires-Dist: h5py!=3.7.0
Requires-Dist: pickleshare>=0.7.5; python_full_version < "3.11"
Provides-Extra: tsfresh
Requires-Dist: tsfresh>=0.21.0; extra == "tsfresh"
Requires-Dist: numba>=0.60; extra == "tsfresh"
Provides-Extra: extras
Requires-Dist: jupyter; extra == "extras"
Requires-Dist: matplotlib; extra == "extras"
Requires-Dist: pyvista; extra == "extras"
Requires-Dist: plotly; extra == "extras"
Requires-Dist: ansys-mapdl-reader; extra == "extras"
Dynamic: license-file
